{
  "page_title": "Assessor Skill Set",
  "page_url": "https://www.rmit.edu.au/study-with-us/levels-of-study/vocational-study/skill-sets/assessor-skill-set-s0189",
  "page_index": 26,
  "chunk_index": 5,
  "total_chunks": 6,
  "text": "nual basis and these fees should only be used as a guide. Payments and refundsFor information on how to pay your fees or how to apply for a refund, please seePaying your fees and applying for refunds. Payments and refunds For information on how to pay your fees or how to apply for a refund, please seePaying your fees and applying for refunds. In addition to tuition fees, you will be charged an annualstudent services and amenities fee (SSAF), which is used to maintain and enhance services and amenities that improve your experience as an RMIT student. The SSAF is calculated based on your enrolment load and the maximum fee for 2025 is $365. Note: SSAF will be charged per nominal hour at a rate of $0.51 per hour in 2025. You may also be required to purchase other items related to your program, including field trips, textbooks and equipment. Theseadditional fees and expensesvary from program to program. There is no fee assistance available for this skill set. RMIT awards more than 2000 scholarships every year to recognise academic achievement and assist students from a variety of backgrounds.Explore scholarships RMIT awards more than 2000 scholarships every year to recognise academic achievement and assist students from a variety of backgrounds. Explore scholarships",
  "structured_data": {
    "course_code": "S0189",
    "campus": "classes"
  },
  "metadata": {
    "start_char": 8820,
    "end_char": 10101,
    "category": "quick-course-scan"
  }
}